Metadata-Version: 2.1
Name: pptx-template-simple
Version: 0.2.8.3
Summary: The PowerPoint presentation builder using template.pptx (without support in cli)
Home-page: https://github.com/Thykof/pptx-template
Author: Thykof
Author-email: thykof@protonmail.ch
License: Apache-2.0
Keywords: powerpoint,ppt,pptx,template
Platform: UNKNOWN
Classifier: Development Status :: 3 - Alpha
Classifier: Topic :: Utilities
Classifier: Programming Language :: Python :: 3
Classifier: License :: OSI Approved :: Apache Software License
Classifier: Operating System :: OS Independent
Requires-Dist: python-pptx
Requires-Dist: pandas
Requires-Dist: openpyxl
Requires-Dist: six
